make_colors/__init__.py
make_colors/__main__.py
make_colors/__version__.py
make_colors/colors.py
make_colors/colors_converter.py
make_colors/hex2ansi.py
make_colors/make_colors.py
make_colors/make_colors1.py
make_colors/make_colors_click.py
make_colors/make_colors_debug.py
make_colors/make_colors_tc.py
make_colors/syntax.py
make_colors/table.py
make_colors/test.py
make_colors/test1.py
make_colors/test2.py
make_colors/test_make_colors.py
make_colors/test_rich_parser.py
make_colors-3.48.14.dist-info/METADATA
make_colors-3.48.14.dist-info/WHEEL
make_colors-3.48.14.dist-info/entry_points.txt
make_colors-3.48.14.dist-info/top_level.txt
make_colors-3.48.14.dist-info/RECORD
