Metadata-Version: 2.4
Name: make_colors
Version: 3.48.14
Summary: A simple, powerful, and cross-platform Python library for adding colors, styles, and rich markup support to your terminal output. Optimized for **Windows 10+**, Linux, and macOS.
Home-page: https://github.com/cumulus13/make_colors
Author: Hadi Cahyadi
Author-email: cumulus13@gmail.com
Maintainer: cumulus13
Maintainer-email: cumulus13@gmail.com
License: MIT
Project-URL: Documentation, https://make_colors.readthedocs.io
Project-URL: Code, https://github.com/cumulus13/make_colors
Project-URL: Issue tracker, https://github.com/cumulus13/make_colors/issues
Keywords: color,terminal,console,ansi,text,colorize,cli,markup,rich_markup
Classifier: Development Status :: 5 - Production/Stable
Classifier: Intended Audience :: Developers
Classifier: Operating System :: OS Independent
Classifier: Programming Language :: Python
Classifier: Programming Language :: Python :: 2
Classifier: Programming Language :: Python :: 2.7
Classifier: Programming Language :: Python :: 3
Classifier: Topic :: Software Development :: Libraries :: Python Modules
Classifier: Topic :: System :: Console Fonts
Classifier: Topic :: Terminals
Classifier: Topic :: Text Processing :: Markup
Requires-Python: >=2.7
Dynamic: author
Dynamic: author-email
Dynamic: classifier
Dynamic: description
Dynamic: description-content-type
Dynamic: home-page
Dynamic: keywords
Dynamic: license
Dynamic: maintainer
Dynamic: maintainer-email
Dynamic: project-url
Dynamic: requires-python
Dynamic: summary
